cube_alchemy/__init__.py
cube_alchemy/catalogs/__init__.py
cube_alchemy/catalogs/abc.py
cube_alchemy/catalogs/service.py
cube_alchemy/catalogs/repository/__init__.py
cube_alchemy/catalogs/repository/in_memory.py
cube_alchemy/catalogs/sources/__init__.py
cube_alchemy/catalogs/sources/yaml_model.py
cube_alchemy/catalogs/sources/yaml_single_file.py
cube_alchemy/catalogs/validation/__init__.py
cube_alchemy/core/__init__.py
cube_alchemy/core/composite_bridge_generator.py
cube_alchemy/core/dependency_index.py
cube_alchemy/core/function_registry.py
cube_alchemy/core/hypercube.py
cube_alchemy/core/metric.py
cube_alchemy/core/schema_validator.py
cube_alchemy/core/spec_validators.py
cube_alchemy/core/hypercube_mixins/__init__.py
cube_alchemy/core/hypercube_mixins/analytics_specs.py
cube_alchemy/core/hypercube_mixins/engine.py
cube_alchemy/core/hypercube_mixins/filter.py
cube_alchemy/core/hypercube_mixins/graph_visualizer.py
cube_alchemy/core/hypercube_mixins/logger.py
cube_alchemy/core/hypercube_mixins/model_catalog.py
cube_alchemy/core/hypercube_mixins/plotting.py
cube_alchemy/core/hypercube_mixins/query.py
cube_alchemy/core/hypercube_mixins/transformation.py
cube_alchemy/plotting/__init__.py
cube_alchemy/plotting/abc_config_resolver.py
cube_alchemy/plotting/abc_plot_renderer.py
cube_alchemy/plotting/matplotlib/__init__.py
cube_alchemy/plotting/matplotlib/matplotlib_renderer.py
cube_alchemy/plotting/matplotlib/handlers/__init__.py
cube_alchemy/plotting/matplotlib/handlers/combo.py
cube_alchemy/plotting/matplotlib/handlers/heatmap.py
cube_alchemy/plotting/matplotlib/handlers/pie.py
cube_alchemy/plotting/matplotlib/handlers/scatter.py
cube_alchemy/plotting/matplotlib/handlers/series.py
cube_alchemy/plotting/matplotlib/handlers/simple_kpi.py
cube_alchemy/plotting/streamlit/__init__.py
cube_alchemy/plotting/streamlit/streamlit_renderer.py
cube_alchemy/plotting/streamlit/handlers/__init__.py
cube_alchemy/plotting/streamlit/handlers/combo.py
cube_alchemy-0.2.4.dist-info/licenses/LICENSE
cube_alchemy-0.2.4.dist-info/METADATA
cube_alchemy-0.2.4.dist-info/WHEEL
cube_alchemy-0.2.4.dist-info/top_level.txt
cube_alchemy-0.2.4.dist-info/RECORD
