Metadata-Version: 2.4
Name: cube-alchemy
Version: 0.2.4
Summary: A lightweight, hypercube engine for multidimensional data analysis
Author-email: "Juan C. Del Monte" <delmontejuan92@gmail.com>
License-Expression: Apache-2.0
Project-URL: Docs, https://cube-alchemy.info
Project-URL: Repository, https://github.com/cube-alchemy/cube-alchemy
Project-URL: Bug Tracker, https://github.com/cube-alchemy/cube-alchemy/issues
Classifier: Programming Language :: Python :: 3
Classifier: Operating System :: OS Independent
Requires-Python: >=3.8
License-File: LICENSE
Requires-Dist: networkx<4.0,>=3.5
Requires-Dist: matplotlib<4.0,>=3.10.3
Requires-Dist: pandas<3.0,>=2.0.0
Requires-Dist: pyyaml<7.0,>=6.0.0
Dynamic: license-file
